CHANGES.rst
DESCRIPTION.rst
LICENSE
MANIFEST.in
README.md
setup.py
src/wai.annotations.roi.egg-info/PKG-INFO
src/wai.annotations.roi.egg-info/SOURCES.txt
src/wai.annotations.roi.egg-info/dependency_links.txt
src/wai.annotations.roi.egg-info/entry_points.txt
src/wai.annotations.roi.egg-info/namespace_packages.txt
src/wai.annotations.roi.egg-info/requires.txt
src/wai.annotations.roi.egg-info/top_level.txt
src/wai/annotations/roi/__init__.py
src/wai/annotations/roi/constants.py
src/wai/annotations/roi/component/_FromROI.py
src/wai/annotations/roi/component/_ROIReader.py
src/wai/annotations/roi/component/_ROIWriter.py
src/wai/annotations/roi/component/_ToROI.py
src/wai/annotations/roi/component/__init__.py
src/wai/annotations/roi/specifier/_ROIInputFormatSpecifier.py
src/wai/annotations/roi/specifier/_ROIOutputFormatSpecifier.py
src/wai/annotations/roi/specifier/__init__.py
src/wai/annotations/roi/util/_ROIObject.py
src/wai/annotations/roi/util/__init__.py
src/wai/annotations/roi/util/_combine_dicts.py
src/wai/annotations/roi/util/_consume_comments.py
src/wai/annotations/roi/util/_filenames.py
src/wai/annotations/roi/util/_format.py
src/wai/annotations/roi/util/_min_rect_from_roi_polygon.py
src/wai/annotations/roi/util/_normalisation.py
src/wai/annotations/roi/util/_roi_polygon.py