Metadata-Version: 2.1
Name: wai.annotations.roi
Version: 1.0.1
Summary: ROI image object-detection format plugins for wai.annotations.
Home-page: https://github.com/waikato-datamining/wai-annotations
Author: Corey Sterling
Author-email: coreytsterling@gmail.com
License: Apache License Version 2.0
Classifier: Development Status :: 4 - Beta
Classifier: License :: OSI Approved :: Apache Software License
Classifier: Topic :: Scientific/Engineering :: Mathematics
Classifier: Programming Language :: Python :: 3
License-File: LICENSE
